{
  "generatedAt": "2026-07-11T01:27:56.170Z",
  "run": {
    "persistOutputs": true,
    "githubActions": true,
    "eventName": "push",
    "runId": "29134541749",
    "headSha": "f56340f297dcc81c3f1d6495fe91efc8df2b90f7"
  },
  "metrics": {
    "sourcesConfigured": 34,
    "sourcesConsulted": 34,
    "candidatesDetected": 87,
    "candidatesIngested": 55,
    "extractionSucceeded": 48,
    "candidatesApproved": 33,
    "discardedDuplicate": 3,
    "duplicateExactUrl": 2,
    "duplicateExactContent": 0,
    "duplicatePublishedEvent": 1,
    "discardedQuality": 12,
    "discardedQualityByReason": {
      "evergreen-or-stale-outside-news-window": 2,
      "undated-discovery": 9,
      "stale-dated-discovery": 1
    },
    "discardedBySourceAndReason": {
      "bing-tolhuin": {
        "evergreen-or-stale-outside-news-window": 1
      },
      "sur54": {
        "undated-discovery": 5
      },
      "critica-sur": {
        "undated-discovery": 4
      },
      "mundo-clarin": {
        "stale-dated-discovery": 1
      },
      "nacionales-cronista": {
        "evergreen-or-stale-outside-news-window": 1
      }
    },
    "discardedGenericTitle": 0,
    "discardedEvergreen": 3,
    "eventsGrouped": 32,
    "verified": 26,
    "pendingVerification": 3,
    "pendingMatchedFromHistory": 5,
    "recentEventRepair": {
      "corrected": 78,
      "compacted": 6,
      "conservedPublished": 11
    },
    "pendingEventsCompacted": 0,
    "pendingCompactionVerified": 0,
    "pendingRecoveryAttempted": 4,
    "pendingTerminalizedExpired": 0,
    "pendingTerminalizedAttempts": 0,
    "pendingAudit": [
      {
        "eventKey": "crime|gobierno|internacional|informa|2026-07-10",
        "title": "Desnudo, maniatado y con los ojos vendados: la imagen de un gazatí detenido por Israel pone el foco en el trato a los presos palestinos",
        "sourceId": "mundo-elpais",
        "publisherDomain": "elpais.com",
        "category": "Mundo",
        "eventType": "crime",
        "lane": "strict",
        "riskLevel": "high",
        "exactReason": "strict-requires-competent-tier-a-or-two-independent-tier-b",
        "missingCondition": "additional-qualified-source",
        "nextRetryAt": "2026-07-11T04:26:05.292Z",
        "expiresAt": "2026-07-13T01:26:05.292Z",
        "corroborationAttempts": 0
      },
      {
        "eventKey": "general|almeria|diferentes|incendio|informe|nacionalidades|serian|victimas|2026-07-11",
        "title": "Informe desde Almería: víctimas del incendio serían de diferentes nacionalidades.",
        "sourceId": "mundo-france24",
        "publisherDomain": "france24.com",
        "category": "Mundo",
        "eventType": "general",
        "lane": "strict",
        "riskLevel": "high",
        "exactReason": "strict-requires-competent-tier-a-or-two-independent-tier-b",
        "missingCondition": "additional-qualified-source",
        "nextRetryAt": "2026-07-11T04:26:05.292Z",
        "expiresAt": "2026-07-13T01:26:05.292Z",
        "corroborationAttempts": 0
      },
      {
        "eventKey": "service|asisten|dolor|heridos|medicos|mirada|mundo|ninos|2026-07-10",
        "title": "\"Ya no quiero ser pediatra. La mirada de esos niños se queda con uno para siempre\": el dolor de los médicos que asisten a los heridos del terremoto en Venezuela - BBC News Mundo",
        "sourceId": "mundo-bbc",
        "publisherDomain": "bbc.com",
        "category": "Mundo",
        "eventType": "service",
        "lane": "strict",
        "riskLevel": "high",
        "exactReason": "strict-requires-competent-tier-a-or-two-independent-tier-b",
        "missingCondition": "additional-qualified-source",
        "nextRetryAt": "2026-07-11T04:26:05.293Z",
        "expiresAt": "2026-07-13T01:26:05.293Z",
        "corroborationAttempts": 1
      }
    ],
    "conflicting": 3,
    "published": 4,
    "publishedByLane": {
      "standard": 1,
      "fast": 1,
      "strict": 2
    },
    "verifiedByLane": {
      "standard": 19,
      "fast": 2,
      "strict": 5
    },
    "pendingByLane": {
      "strict": 3
    },
    "eventsByTerritory": {
      "Nacionales": 13,
      "Ushuaia": 4,
      "Rio Grande": 1,
      "Tolhuin": 2,
      "Mundo": 12
    },
    "verifiedByTerritory": {
      "Nacionales": 11,
      "Ushuaia": 4,
      "Rio Grande": 1,
      "Tolhuin": 2,
      "Mundo": 8
    },
    "fastPendingAudit": [],
    "freshCandidates": 36,
    "staleDiscarded": 3,
    "sourceHealth": {
      "rio-grande-oficial": {
        "detected": 4,
        "materialized": 0,
        "freshCandidates": 0,
        "qualityDiscarded": 0,
        "staleDiscarded": 0,
        "consulted": 1,
        "fetchErrors": 0,
        "noItems": 0,
        "lastError": "",
        "status": "idle",
        "issueCategory": "no-new-materializable-items",
        "verifiedContribution": 0,
        "publicationContribution": 0,
        "freshCandidateRate": 0,
        "materializationSuccessRate": 0,
        "verificationContributionRate": 0,
        "publicationContributionRate": 0,
        "staleDiscardRate": 0
      },
      "ushuaia-oficial": {
        "detected": 0,
        "materialized": 0,
        "freshCandidates": 0,
        "qualityDiscarded": 0,
        "staleDiscarded": 0,
        "consulted": 1,
        "fetchErrors": 1,
        "noItems": 0,
        "lastError": "fetch failed",
        "status": "unhealthy",
        "issueCategory": "fetch-error",
        "verifiedContribution": 0,
        "publicationContribution": 0,
        "freshCandidateRate": 0,
        "materializationSuccessRate": 0,
        "verificationContributionRate": 0,
        "publicationContributionRate": 0,
        "staleDiscardRate": 0
      },
      "gobierno-tdf-oficial": {
        "detected": 5,
        "materialized": 0,
        "freshCandidates": 0,
        "qualityDiscarded": 0,
        "staleDiscarded": 0,
        "consulted": 1,
        "fetchErrors": 0,
        "noItems": 0,
        "lastError": "",
        "status": "idle",
        "issueCategory": "no-new-materializable-items",
        "verifiedContribution": 0,
        "publicationContribution": 0,
        "freshCandidateRate": 0,
        "materializationSuccessRate": 0,
        "verificationContributionRate": 0,
        "publicationContributionRate": 0,
        "staleDiscardRate": 0
      },
      "tolhuin-oficial": {
        "detected": 4,
        "materialized": 0,
        "freshCandidates": 0,
        "qualityDiscarded": 0,
        "staleDiscarded": 0,
        "consulted": 1,
        "fetchErrors": 0,
        "noItems": 0,
        "lastError": "",
        "status": "idle",
        "issueCategory": "no-new-materializable-items",
        "verifiedContribution": 0,
        "publicationContribution": 0,
        "freshCandidateRate": 0,
        "materializationSuccessRate": 0,
        "verificationContributionRate": 0,
        "publicationContributionRate": 0,
        "staleDiscardRate": 0
      },
      "actualidad-tdf": {
        "detected": 0,
        "materialized": 0,
        "freshCandidates": 0,
        "qualityDiscarded": 0,
        "staleDiscarded": 0,
        "consulted": 1,
        "fetchErrors": 1,
        "noItems": 0,
        "lastError": "HTTP 500 en https://www.actualidadtdf.com.ar/feed/",
        "status": "unhealthy",
        "issueCategory": "fetch-error",
        "verifiedContribution": 0,
        "publicationContribution": 0,
        "freshCandidateRate": 0,
        "materializationSuccessRate": 0,
        "verificationContributionRate": 0,
        "publicationContributionRate": 0,
        "staleDiscardRate": 0
      },
      "el-rompehielos": {
        "detected": 4,
        "materialized": 0,
        "freshCandidates": 0,
        "qualityDiscarded": 0,
        "staleDiscarded": 0,
        "consulted": 1,
        "fetchErrors": 0,
        "noItems": 0,
        "lastError": "",
        "status": "idle",
        "issueCategory": "no-new-materializable-items",
        "verifiedContribution": 0,
        "publicationContribution": 0,
        "freshCandidateRate": 0,
        "materializationSuccessRate": 0,
        "verificationContributionRate": 0,
        "publicationContributionRate": 0,
        "staleDiscardRate": 0
      },
      "radiofueguina": {
        "detected": 3,
        "materialized": 0,
        "freshCandidates": 0,
        "qualityDiscarded": 0,
        "staleDiscarded": 0,
        "consulted": 1,
        "fetchErrors": 0,
        "noItems": 0,
        "lastError": "",
        "status": "idle",
        "issueCategory": "no-new-materializable-items",
        "verifiedContribution": 0,
        "publicationContribution": 0,
        "freshCandidateRate": 0,
        "materializationSuccessRate": 0,
        "verificationContributionRate": 0,
        "publicationContributionRate": 0,
        "staleDiscardRate": 0
      },
      "radio-universidad": {
        "detected": 4,
        "materialized": 4,
        "freshCandidates": 4,
        "qualityDiscarded": 0,
        "staleDiscarded": 0,
        "consulted": 1,
        "fetchErrors": 0,
        "noItems": 0,
        "lastError": "",
        "status": "healthy",
        "issueCategory": "",
        "verifiedContribution": 3,
        "publicationContribution": 2,
        "freshCandidateRate": 1,
        "materializationSuccessRate": 1,
        "verificationContributionRate": 0.75,
        "publicationContributionRate": 0.5,
        "staleDiscardRate": 0
      },
      "sur54": {
        "detected": 5,
        "materialized": 5,
        "freshCandidates": 0,
        "qualityDiscarded": 5,
        "staleDiscarded": 0,
        "consulted": 1,
        "fetchErrors": 0,
        "noItems": 0,
        "lastError": "",
        "status": "degraded",
        "issueCategory": "zero-useful-candidates",
        "verifiedContribution": 0,
        "publicationContribution": 0,
        "freshCandidateRate": 0,
        "materializationSuccessRate": 1,
        "verificationContributionRate": 0,
        "publicationContributionRate": 0,
        "staleDiscardRate": 0
      },
      "ushuaia24": {
        "detected": 4,
        "materialized": 3,
        "freshCandidates": 3,
        "qualityDiscarded": 0,
        "staleDiscarded": 0,
        "consulted": 1,
        "fetchErrors": 0,
        "noItems": 0,
        "lastError": "",
        "status": "healthy",
        "issueCategory": "",
        "verifiedContribution": 3,
        "publicationContribution": 0,
        "freshCandidateRate": 0.75,
        "materializationSuccessRate": 0.75,
        "verificationContributionRate": 0.75,
        "publicationContributionRate": 0,
        "staleDiscardRate": 0
      },
      "provincia23": {
        "detected": 3,
        "materialized": 0,
        "freshCandidates": 0,
        "qualityDiscarded": 0,
        "staleDiscarded": 0,
        "consulted": 1,
        "fetchErrors": 0,
        "noItems": 0,
        "lastError": "",
        "status": "idle",
        "issueCategory": "no-new-materializable-items",
        "verifiedContribution": 0,
        "publicationContribution": 0,
        "freshCandidateRate": 0,
        "materializationSuccessRate": 0,
        "verificationContributionRate": 0,
        "publicationContributionRate": 0,
        "staleDiscardRate": 0
      },
      "critica-sur": {
        "detected": 4,
        "materialized": 4,
        "freshCandidates": 0,
        "qualityDiscarded": 4,
        "staleDiscarded": 0,
        "consulted": 1,
        "fetchErrors": 0,
        "noItems": 0,
        "lastError": "",
        "status": "degraded",
        "issueCategory": "zero-useful-candidates",
        "verifiedContribution": 0,
        "publicationContribution": 0,
        "freshCandidateRate": 0,
        "materializationSuccessRate": 1,
        "verificationContributionRate": 0,
        "publicationContributionRate": 0,
        "staleDiscardRate": 0
      },
      "bing-tdf": {
        "detected": 5,
        "materialized": 0,
        "freshCandidates": 0,
        "qualityDiscarded": 0,
        "staleDiscarded": 0,
        "consulted": 1,
        "fetchErrors": 0,
        "noItems": 0,
        "lastError": "",
        "status": "idle",
        "issueCategory": "no-new-materializable-items",
        "verifiedContribution": 0,
        "publicationContribution": 0,
        "freshCandidateRate": 0,
        "materializationSuccessRate": 0,
        "verificationContributionRate": 0,
        "publicationContributionRate": 0,
        "staleDiscardRate": 0
      },
      "bing-rio-grande": {
        "detected": 4,
        "materialized": 0,
        "freshCandidates": 0,
        "qualityDiscarded": 0,
        "staleDiscarded": 0,
        "consulted": 1,
        "fetchErrors": 0,
        "noItems": 0,
        "lastError": "",
        "status": "idle",
        "issueCategory": "no-new-materializable-items",
        "verifiedContribution": 0,
        "publicationContribution": 0,
        "freshCandidateRate": 0,
        "materializationSuccessRate": 0,
        "verificationContributionRate": 0,
        "publicationContributionRate": 0,
        "staleDiscardRate": 0
      },
      "bing-ushuaia": {
        "detected": 0,
        "materialized": 0,
        "freshCandidates": 0,
        "qualityDiscarded": 0,
        "staleDiscarded": 0,
        "consulted": 1,
        "fetchErrors": 1,
        "noItems": 0,
        "lastError": "Feed not recognized as RSS 1 or 2.",
        "status": "unhealthy",
        "issueCategory": "fetch-error",
        "verifiedContribution": 0,
        "publicationContribution": 0,
        "freshCandidateRate": 0,
        "materializationSuccessRate": 0,
        "verificationContributionRate": 0,
        "publicationContributionRate": 0,
        "staleDiscardRate": 0
      },
      "bing-tolhuin": {
        "detected": 0,
        "materialized": 1,
        "freshCandidates": 0,
        "qualityDiscarded": 1,
        "staleDiscarded": 1,
        "consulted": 1,
        "fetchErrors": 1,
        "noItems": 0,
        "lastError": "Unquoted attribute value\nLine: 0\nColumn: 42\nChar: h",
        "status": "unhealthy",
        "issueCategory": "fetch-error",
        "verifiedContribution": 0,
        "publicationContribution": 0,
        "freshCandidateRate": 0,
        "materializationSuccessRate": 0,
        "verificationContributionRate": 0,
        "publicationContributionRate": 0,
        "staleDiscardRate": 0
      },
      "bing-malvinas": {
        "detected": 0,
        "materialized": 0,
        "freshCandidates": 0,
        "qualityDiscarded": 0,
        "staleDiscarded": 0,
        "consulted": 1,
        "fetchErrors": 1,
        "noItems": 0,
        "lastError": "Unquoted attribute value\nLine: 0\nColumn: 42\nChar: h",
        "status": "unhealthy",
        "issueCategory": "fetch-error",
        "verifiedContribution": 0,
        "publicationContribution": 0,
        "freshCandidateRate": 0,
        "materializationSuccessRate": 0,
        "verificationContributionRate": 0,
        "publicationContributionRate": 0,
        "staleDiscardRate": 0
      },
      "bing-antartida": {
        "detected": 3,
        "materialized": 0,
        "freshCandidates": 0,
        "qualityDiscarded": 0,
        "staleDiscarded": 0,
        "consulted": 1,
        "fetchErrors": 0,
        "noItems": 0,
        "lastError": "",
        "status": "idle",
        "issueCategory": "no-new-materializable-items",
        "verifiedContribution": 0,
        "publicationContribution": 0,
        "freshCandidateRate": 0,
        "materializationSuccessRate": 0,
        "verificationContributionRate": 0,
        "publicationContributionRate": 0,
        "staleDiscardRate": 0
      },
      "infobae-tdf": {
        "detected": 0,
        "materialized": 0,
        "freshCandidates": 0,
        "qualityDiscarded": 0,
        "staleDiscarded": 0,
        "consulted": 1,
        "fetchErrors": 0,
        "noItems": 1,
        "lastError": "",
        "status": "unhealthy",
        "issueCategory": "zero-items",
        "verifiedContribution": 0,
        "publicationContribution": 0,
        "freshCandidateRate": 0,
        "materializationSuccessRate": 0,
        "verificationContributionRate": 0,
        "publicationContributionRate": 0,
        "staleDiscardRate": 0
      },
      "perfil-tdf": {
        "detected": 0,
        "materialized": 0,
        "freshCandidates": 0,
        "qualityDiscarded": 0,
        "staleDiscarded": 0,
        "consulted": 1,
        "fetchErrors": 0,
        "noItems": 1,
        "lastError": "",
        "status": "unhealthy",
        "issueCategory": "zero-items",
        "verifiedContribution": 0,
        "publicationContribution": 0,
        "freshCandidateRate": 0,
        "materializationSuccessRate": 0,
        "verificationContributionRate": 0,
        "publicationContributionRate": 0,
        "staleDiscardRate": 0
      },
      "clarin-tdf": {
        "detected": 0,
        "materialized": 0,
        "freshCandidates": 0,
        "qualityDiscarded": 0,
        "staleDiscarded": 0,
        "consulted": 1,
        "fetchErrors": 0,
        "noItems": 1,
        "lastError": "",
        "status": "unhealthy",
        "issueCategory": "zero-items",
        "verifiedContribution": 0,
        "publicationContribution": 0,
        "freshCandidateRate": 0,
        "materializationSuccessRate": 0,
        "verificationContributionRate": 0,
        "publicationContributionRate": 0,
        "staleDiscardRate": 0
      },
      "nacionales-infobae": {
        "detected": 3,
        "materialized": 5,
        "freshCandidates": 5,
        "qualityDiscarded": 0,
        "staleDiscarded": 0,
        "consulted": 1,
        "fetchErrors": 0,
        "noItems": 0,
        "lastError": "",
        "status": "healthy",
        "issueCategory": "",
        "verifiedContribution": 4,
        "publicationContribution": 0,
        "freshCandidateRate": 1,
        "materializationSuccessRate": 1,
        "verificationContributionRate": 0.8,
        "publicationContributionRate": 0,
        "staleDiscardRate": 0
      },
      "nacionales-perfil": {
        "detected": 2,
        "materialized": 2,
        "freshCandidates": 2,
        "qualityDiscarded": 0,
        "staleDiscarded": 0,
        "consulted": 1,
        "fetchErrors": 0,
        "noItems": 0,
        "lastError": "",
        "status": "healthy",
        "issueCategory": "",
        "verifiedContribution": 1,
        "publicationContribution": 0,
        "freshCandidateRate": 1,
        "materializationSuccessRate": 1,
        "verificationContributionRate": 0.5,
        "publicationContributionRate": 0,
        "staleDiscardRate": 0
      },
      "nacionales-la-nacion": {
        "detected": 3,
        "materialized": 3,
        "freshCandidates": 3,
        "qualityDiscarded": 0,
        "staleDiscarded": 0,
        "consulted": 1,
        "fetchErrors": 0,
        "noItems": 0,
        "lastError": "",
        "status": "healthy",
        "issueCategory": "",
        "verifiedContribution": 2,
        "publicationContribution": 0,
        "freshCandidateRate": 1,
        "materializationSuccessRate": 1,
        "verificationContributionRate": 0.67,
        "publicationContributionRate": 0,
        "staleDiscardRate": 0
      },
      "nacionales-ambito": {
        "detected": 3,
        "materialized": 3,
        "freshCandidates": 3,
        "qualityDiscarded": 0,
        "staleDiscarded": 0,
        "consulted": 1,
        "fetchErrors": 0,
        "noItems": 0,
        "lastError": "",
        "status": "healthy",
        "issueCategory": "",
        "verifiedContribution": 2,
        "publicationContribution": 0,
        "freshCandidateRate": 1,
        "materializationSuccessRate": 1,
        "verificationContributionRate": 0.67,
        "publicationContributionRate": 0,
        "staleDiscardRate": 0
      },
      "nacionales-cronista": {
        "detected": 3,
        "materialized": 3,
        "freshCandidates": 2,
        "qualityDiscarded": 1,
        "staleDiscarded": 1,
        "consulted": 1,
        "fetchErrors": 0,
        "noItems": 0,
        "lastError": "",
        "status": "healthy",
        "issueCategory": "",
        "verifiedContribution": 2,
        "publicationContribution": 0,
        "freshCandidateRate": 0.67,
        "materializationSuccessRate": 1,
        "verificationContributionRate": 0.67,
        "publicationContributionRate": 0,
        "staleDiscardRate": 0.33
      },
      "nacionales-tn": {
        "detected": 3,
        "materialized": 1,
        "freshCandidates": 1,
        "qualityDiscarded": 0,
        "staleDiscarded": 0,
        "consulted": 1,
        "fetchErrors": 0,
        "noItems": 0,
        "lastError": "",
        "status": "healthy",
        "issueCategory": "",
        "verifiedContribution": 1,
        "publicationContribution": 0,
        "freshCandidateRate": 0.33,
        "materializationSuccessRate": 0.33,
        "verificationContributionRate": 0.33,
        "publicationContributionRate": 0,
        "staleDiscardRate": 0
      },
      "mundo-google": {
        "detected": 3,
        "materialized": 0,
        "freshCandidates": 0,
        "qualityDiscarded": 0,
        "staleDiscarded": 0,
        "consulted": 1,
        "fetchErrors": 0,
        "noItems": 0,
        "lastError": "",
        "status": "idle",
        "issueCategory": "no-new-materializable-items",
        "verifiedContribution": 0,
        "publicationContribution": 0,
        "freshCandidateRate": 0,
        "materializationSuccessRate": 0,
        "verificationContributionRate": 0,
        "publicationContributionRate": 0,
        "staleDiscardRate": 0
      },
      "mundo-clarin": {
        "detected": 3,
        "materialized": 2,
        "freshCandidates": 1,
        "qualityDiscarded": 1,
        "staleDiscarded": 1,
        "consulted": 1,
        "fetchErrors": 0,
        "noItems": 0,
        "lastError": "",
        "status": "healthy",
        "issueCategory": "",
        "verifiedContribution": 0,
        "publicationContribution": 0,
        "freshCandidateRate": 0.33,
        "materializationSuccessRate": 0.67,
        "verificationContributionRate": 0,
        "publicationContributionRate": 0,
        "staleDiscardRate": 0.33
      },
      "mundo-bbc": {
        "detected": 3,
        "materialized": 3,
        "freshCandidates": 3,
        "qualityDiscarded": 0,
        "staleDiscarded": 0,
        "consulted": 1,
        "fetchErrors": 0,
        "noItems": 0,
        "lastError": "",
        "status": "healthy",
        "issueCategory": "",
        "verifiedContribution": 2,
        "publicationContribution": 0,
        "freshCandidateRate": 1,
        "materializationSuccessRate": 1,
        "verificationContributionRate": 0.67,
        "publicationContributionRate": 0,
        "staleDiscardRate": 0
      },
      "mundo-dw": {
        "detected": 3,
        "materialized": 3,
        "freshCandidates": 3,
        "qualityDiscarded": 0,
        "staleDiscarded": 0,
        "consulted": 1,
        "fetchErrors": 0,
        "noItems": 0,
        "lastError": "",
        "status": "healthy",
        "issueCategory": "",
        "verifiedContribution": 3,
        "publicationContribution": 1,
        "freshCandidateRate": 1,
        "materializationSuccessRate": 1,
        "verificationContributionRate": 1,
        "publicationContributionRate": 0.33,
        "staleDiscardRate": 0
      },
      "mundo-france24": {
        "detected": 3,
        "materialized": 3,
        "freshCandidates": 3,
        "qualityDiscarded": 0,
        "staleDiscarded": 0,
        "consulted": 1,
        "fetchErrors": 0,
        "noItems": 0,
        "lastError": "",
        "status": "healthy",
        "issueCategory": "",
        "verifiedContribution": 2,
        "publicationContribution": 1,
        "freshCandidateRate": 1,
        "materializationSuccessRate": 1,
        "verificationContributionRate": 0.67,
        "publicationContributionRate": 0.33,
        "staleDiscardRate": 0
      },
      "mundo-elpais": {
        "detected": 3,
        "materialized": 3,
        "freshCandidates": 3,
        "qualityDiscarded": 0,
        "staleDiscarded": 0,
        "consulted": 1,
        "fetchErrors": 0,
        "noItems": 0,
        "lastError": "",
        "status": "healthy",
        "issueCategory": "",
        "verifiedContribution": 2,
        "publicationContribution": 0,
        "freshCandidateRate": 1,
        "materializationSuccessRate": 1,
        "verificationContributionRate": 0.67,
        "publicationContributionRate": 0,
        "staleDiscardRate": 0
      },
      "mundo-bing": {
        "detected": 0,
        "materialized": 0,
        "freshCandidates": 0,
        "qualityDiscarded": 0,
        "staleDiscarded": 0,
        "consulted": 1,
        "fetchErrors": 1,
        "noItems": 0,
        "lastError": "Unquoted attribute value\nLine: 0\nColumn: 42\nChar: h",
        "status": "unhealthy",
        "issueCategory": "fetch-error",
        "verifiedContribution": 0,
        "publicationContribution": 0,
        "freshCandidateRate": 0,
        "materializationSuccessRate": 0,
        "verificationContributionRate": 0,
        "publicationContributionRate": 0,
        "staleDiscardRate": 0
      }
    },
    "sourceDeprioritized": [],
    "drafts": 9,
    "modelErrors": 0,
    "publicationErrors": 0,
    "factualValidationErrors": 3,
    "discardedImportance": 7,
    "discardedSourceLimit": 1,
    "discardedNoAiBudget": 9,
    "budgetDeferred": 9,
    "failedRetryable": 0,
    "failedTerminal": 0,
    "failedRetryableByReason": {},
    "failedTerminalByReason": {},
    "aiReused": 0,
    "rescueQueued": 0,
    "rescueAttempted": 0,
    "rescueSucceeded": 0,
    "rescueExhausted": 0,
    "discardedPublicationLimit": 2,
    "extractErrors": 0,
    "imageErrors": 0,
    "aiAttempts": 16,
    "aiCalls": 16,
    "articlesDrafted": 13,
    "imagesResolved": 4,
    "approvedForPublication": 4,
    "imageSelections": [
      {
        "title": "Emprender TDF celebra el Día del Amigo con feria en Tolhuin y Ushuaia",
        "strategy": "article-og",
        "query": "Emprender TDF tendrá una edición especial por el Día del Amigo en Tolhuin y Ushuaia | radiouniversidad.com.ar",
        "score": 82,
        "source": "https://www.radiouniversidad.com.ar/wp-content/uploads/2026/07/07-5-scaled.jpg"
      },
      {
        "title": "Éxito del FigusFest en el Centro Cultural Nueva Argentina de Ushuaia",
        "strategy": "article-og",
        "query": "Multitudinario FigusFest en el Centro Cultural “Nueva Argentina” | radiouniversidad.com.ar",
        "score": 82,
        "source": "https://www.radiouniversidad.com.ar/wp-content/uploads/2026/07/06-5-scaled.jpg"
      },
      {
        "title": "Tensión entre EE. UU. e Irán: Donald Trump endurece su postura",
        "strategy": "article-og",
        "query": "EE. UU.-Irán: Donald Trump entierra la tregua y endurece su discurso contra Teherán",
        "score": 82,
        "source": "https://s.france24.com/media/display/57a6b538-7cb8-11f1-aed4-005056bf30b7/w:1280/p:16x9/ES-20260710-180152-180305-CS.jpg"
      },
      {
        "title": "Zelenski crea fuerza militar de reacción rápida para Ucrania",
        "strategy": "article-og",
        "query": "Zelenski crea fuerza militar de reacción rápida para Ucrania",
        "score": 82,
        "source": "https://static.dw.com/image/75135657_6.jpg"
      }
    ],
    "agendaStories": 242,
    "newsworthinessAverage": 67,
    "newsworthinessTop": [
      {
        "title": "Scioli llegó a Ushuaia para inaugurar el primer vuelo directo entre São Paulo y la capital fueguina",
        "eventKey": "service|capital|directo|fueguina|inaugurar|llego|paulo|primer|rio grande|ushuaia|2026-07-09",
        "score": 100,
        "topic": "servicios",
        "territory": "Ushuaia",
        "lane": "standard"
      },
      {
        "title": "Emprender TDF tendrá una edición especial por el Día del Amigo en Tolhuin y Ushuaia | radiouniversidad.com.ar",
        "eventKey": "service|amigo|edicion|emprender|especial|radiouniversidad|tendra|rio grande|ushuaia|2026-07-10",
        "score": 100,
        "topic": "servicios",
        "territory": "Tolhuin",
        "lane": "standard"
      },
      {
        "title": "Multitudinario FigusFest en el Centro Cultural “Nueva Argentina” | radiouniversidad.com.ar",
        "eventKey": "agenda|argentina|centro|cultural|figusfest|multitudinario|nueva|radiouniversidad|ushuaia|tierra del fuego|2026-07-10",
        "score": 100,
        "topic": "agenda",
        "territory": "Ushuaia",
        "lane": "fast"
      },
      {
        "title": "EE. UU.-Irán: Donald Trump entierra la tregua y endurece su discurso contra Teherán",
        "eventKey": "international-conflict|otan|donald trump|new york post|internacional|estados unidos|informa|2026-07-10",
        "score": 88,
        "topic": "politica",
        "territory": "Mundo",
        "lane": "strict"
      },
      {
        "title": "Cuánto necesito para irme de vacaciones de invierno a Bariloche, Brasil o Chile y las opciones “low cost”",
        "eventKey": "general|bariloche|brasil|chile|cuanto|invierno|necesito|opciones|ushuaia|tierra del fuego|2026-07-11",
        "score": 86,
        "topic": "economia",
        "territory": "Ushuaia",
        "lane": "standard"
      },
      {
        "title": "Zelenski crea fuerza militar de reacción rápida para Ucrania",
        "eventKey": "international-conflict|internacional|informa|2026-07-11",
        "score": 85,
        "topic": "politica",
        "territory": "Mundo",
        "lane": "strict"
      },
      {
        "title": "Así estará el tiempo este fin de semana en Ushuaia",
        "eventKey": "general|estara|semana|tiempo|rio grande|ushuaia|2026-07-10",
        "score": 74,
        "topic": "sociedad",
        "territory": "Ushuaia",
        "lane": "fast"
      },
      {
        "title": "Río Grande habilitó el primer tramo pavimentado de la calle Punta Popper",
        "eventKey": "general|calle|habilito|pavimentado|popper|primer|punta|tramo|rio grande|ushuaia|2026-07-10",
        "score": 74,
        "topic": "sociedad",
        "territory": "Rio Grande",
        "lane": "standard"
      },
      {
        "title": "Harrington destacó el trabajo conjunto entre el BTF, GADA S.A. y el Municipio para ampliar el acceso a la vivienda | radiouniversidad.com.ar",
        "eventKey": "general|acceso|ampliar|conjunto|destaco|harrington|radiouniversidad|trabajo|tolhuin|tierra del fuego|2026-07-10",
        "score": 71,
        "topic": "sociedad",
        "territory": "Tolhuin",
        "lane": "standard"
      },
      {
        "title": "Lionel Scaloni habla en conferencia de prensa antes del partido de Argentina ante Suiza por los cuartos de final del Mundial 2026",
        "eventKey": "general|antes|argentina|conferencia|cuartos|final|habla|lionel|2026-07-11",
        "score": 60,
        "topic": "deportes",
        "territory": "Nacionales",
        "lane": "standard"
      }
    ],
    "corroborationSearches": 3,
    "corroborationFound": 3,
    "corroborationVerified": 1,
    "corroborationConflicts": 1,
    "corroborationNoResult": 2,
    "corroborationAttempts": [
      {
        "eventKey": "service|asisten|dolor|heridos|medicos|mirada|mundo|ninos|2026-07-10",
        "title": "\"Ya no quiero ser pediatra. La mirada de esos niños se queda con uno para siempre\": el dolor de los médicos que asisten a los heridos del terremoto en Venezuela - BBC News Mundo",
        "priorityRank": 1,
        "corroborationQuery": "BBC News Mundo Agotados Universidad Central de Venezuela Venezuela Francia Espana asisten dolor heridos medicos mirada mundo",
        "corroborationReason": "newsworthiness=100; freshness=25h; territory=Mundo; impact=22; corroborability=10; pendingAge=25h; attempts=0",
        "found": 0,
        "verified": false,
        "status": "fetch-error"
      },
      {
        "eventKey": "international-conflict|internacional|informa|2026-07-11",
        "title": "Zelenski crea fuerza militar de reacción rápida para Ucrania",
        "priorityRank": 2,
        "corroborationQuery": "conflicto fuerza militar rapida reaccion ucrania zelenski",
        "corroborationReason": "newsworthiness=91; freshness=1h; territory=Mundo; impact=12; corroborability=10; pendingAge=1h; attempts=0",
        "found": 1,
        "verified": true,
        "status": "verified-strict"
      },
      {
        "eventKey": "general|catastrofe|cuatro|muertos|semanas|sismos|venezuela|2026-07-10",
        "title": "Sismos en Venezuela: a dos semanas de la catástrofe ya son más de cuatro mil los muertos",
        "priorityRank": 3,
        "corroborationQuery": "ONU Argentina Venezuela Espana catastrofe cuatro muertos semanas sismos",
        "corroborationReason": "newsworthiness=85; freshness=3h; territory=Mundo; impact=10; corroborability=10; pendingAge=3h; attempts=0",
        "found": 2,
        "verified": false,
        "status": "conflicting-sources"
      }
    ],
    "conflictsByField": {
      "dates": 4,
      "casualties": 3,
      "money": 3,
      "percentages": 1
    },
    "criticalConflicts": 5,
    "nonCriticalDifferences": 6,
    "resolvedComplementaryFacts": 57,
    "latency": {
      "discoveryToVerificationMinutes": {
        "count": 14,
        "avg": 149.2,
        "p50": 0,
        "max": 1384.3
      },
      "verificationToPublicationMinutes": {
        "count": 14,
        "avg": 10.6,
        "p50": 0.2,
        "max": 145.8
      },
      "discoveryToPublicationMinutes": {
        "count": 14,
        "avg": 159.8,
        "p50": 0.3,
        "max": 1384.4
      },
      "discoveryToVerificationAllMinutes": {
        "count": 55,
        "avg": 124,
        "p50": 0,
        "max": 2101.9
      },
      "cohort": {
        "comparablePublishedCount": 14,
        "verifiedWithoutPublicationCount": 41,
        "publicationWithoutVerifiedAtCount": 1,
        "invalidTimestampCount": 0,
        "comparableDefinition": "firstDetectedAt <= verifiedAt <= publishedAt"
      }
    },
    "byCategory": {
      "Provincia": 2,
      "Mundo": 2
    },
    "publishedLast3hBeforeRun": 2,
    "publishedLast6hBeforeRun": 6,
    "publishedLast12hBeforeRun": 7,
    "publishedLast24hBeforeRun": 9,
    "hoursSinceLastPublicationBeforeRun": 2.4,
    "dailyTarget": {
      "min": 12,
      "max": 16,
      "publishedLast24hBeforeRun": 9,
      "remainingToMin": 3,
      "slotsRemaining": 7,
      "effectiveRunTarget": 3,
      "effectiveRunMaxNormal": 4
    },
    "agendaTop": [
      {
        "storyId": "service|asisten|dolor|heridos|medicos|mirada|mundo|ninos|2026-07-10",
        "headlineSeed": "\"Ya no quiero ser pediatra. La mirada de esos niños se queda con uno para siempre\": el dolor de los médicos que asisten a los heridos del terremoto en Venezuela - BBC News Mundo",
        "topic": "servicios",
        "territory": "Mundo",
        "newsworthinessScore": 100,
        "status": "pending-verification",
        "scoreBreakdown": {
          "publicInterest": 23,
          "localRelevance": 7,
          "impactMagnitude": 23,
          "serviceValue": 20,
          "socialPotential": 7,
          "searchPotential": 15,
          "recency": 9,
          "sourceStrength": 3,
          "diversity": 4
        }
      },
      {
        "storyId": "general|catastrofe|cuatro|muertos|semanas|sismos|venezuela|2026-07-10",
        "headlineSeed": "Sismos en Venezuela: a dos semanas de la catástrofe ya son más de cuatro mil los muertos",
        "topic": "servicios",
        "territory": "Mundo",
        "newsworthinessScore": 100,
        "status": "conflicting-sources",
        "scoreBreakdown": {
          "publicInterest": 23,
          "localRelevance": 7,
          "impactMagnitude": 23,
          "serviceValue": 20,
          "socialPotential": 4,
          "searchPotential": 15,
          "recency": 15,
          "sourceStrength": 3,
          "diversity": 4
        }
      },
      {
        "storyId": "agenda|argentina|centro|cultural|figusfest|multitudinario|nueva|radiouniversidad|ushuaia|tierra del fuego|2026-07-10",
        "headlineSeed": "Multitudinario FigusFest en el Centro Cultural “Nueva Argentina” | radiouniversidad.com.ar",
        "topic": "agenda",
        "territory": "Ushuaia",
        "newsworthinessScore": 100,
        "status": "published",
        "scoreBreakdown": {
          "publicInterest": 15,
          "localRelevance": 25,
          "impactMagnitude": 0,
          "serviceValue": 20,
          "socialPotential": 15,
          "searchPotential": 13,
          "recency": 12,
          "sourceStrength": 3,
          "diversity": 0
        }
      },
      {
        "storyId": "service|capital|directo|fueguina|inaugurar|llego|paulo|primer|rio grande|ushuaia|2026-07-09",
        "headlineSeed": "Scioli llegó a Ushuaia para inaugurar el primer vuelo directo entre São Paulo y la capital fueguina",
        "topic": "servicios",
        "territory": "Ushuaia",
        "newsworthinessScore": 100,
        "status": "verified-standard-single-source",
        "scoreBreakdown": {
          "publicInterest": 18,
          "localRelevance": 25,
          "impactMagnitude": 0,
          "serviceValue": 20,
          "socialPotential": 11,
          "searchPotential": 13,
          "recency": 15,
          "sourceStrength": 3,
          "diversity": 4
        }
      },
      {
        "storyId": "service|amigo|edicion|emprender|especial|radiouniversidad|tendra|rio grande|ushuaia|2026-07-10",
        "headlineSeed": "Emprender TDF tendrá una edición especial por el Día del Amigo en Tolhuin y Ushuaia | radiouniversidad.com.ar",
        "topic": "servicios",
        "territory": "Tolhuin",
        "newsworthinessScore": 100,
        "status": "published",
        "scoreBreakdown": {
          "publicInterest": 18,
          "localRelevance": 25,
          "impactMagnitude": 0,
          "serviceValue": 20,
          "socialPotential": 11,
          "searchPotential": 13,
          "recency": 12,
          "sourceStrength": 3,
          "diversity": 0
        }
      }
    ],
    "agendaInvalidStories": 26,
    "technicalSuccess": true,
    "editorialOutcome": "published",
    "sourceHealthSummary": {
      "configured": 34,
      "consulted": 34,
      "healthy": 25,
      "productive": 13,
      "noResults": 3,
      "failed": 6
    }
  },
  "budget": {
    "maxAiPerRun": 16,
    "officialAiUsed": 0,
    "officialAiBudget": 0,
    "discoveryAiUsed": 16,
    "discoveryAiBudget": 16,
    "aiConcurrency": 1,
    "maxRetryAttempts": 3,
    "maxRescuePerRun": 4,
    "maxPendingRecoveryPerRun": 4,
    "maxPendingCorroborationAttempts": 4,
    "targetPublishedPerRun": 3,
    "effectiveRunTarget": 3,
    "maxNormalPublishedPerRun": 4,
    "effectiveRunMaxNormal": 4,
    "extraSlotMinImportance": 8,
    "dailyTargetMin": 12,
    "dailyTargetMax": 16,
    "publishedLast24hBeforeRun": 9,
    "candidatesMaterialized": 48,
    "totalCandidatesBeforeLimit": 55
  },
  "reasonNoMorePublished": [
    "3 evento(s) quedaron pendientes de segunda fuente",
    "3 evento(s) tuvieron conflicto factual",
    "3 candidato(s) descartados por duplicado/similitud",
    "12 candidato(s) descartados por causas especificas (evergreen-or-stale-outside-news-window: 2, undated-discovery: 9, stale-dated-discovery: 1)",
    "7 candidato(s) descartados por importancia editorial",
    "1 candidato(s) quedaron por limite por fuente",
    "9 candidato(s) quedaron sin presupuesto IA",
    "2 candidato(s) quedaron por cupo editorial de corrida",
    "3 candidato(s) bloqueados por validacion factual",
    "7 candidato(s) no se materializaron por limite anti-timeout"
  ]
}
