{
  "generatedAt": "2026-07-20T06:51:31.128Z",
  "summary": {
    "configured": 34,
    "healthy": 28,
    "unhealthy": 6,
    "productive": 28,
    "zeroResults": 0,
    "failed": 5
  },
  "sources": [
    {
      "id": "rio-grande-oficial",
      "name": "Municipio de Río Grande",
      "type": "rss",
      "itemsFetched": 1,
      "linksResolved": 1,
      "articlesExtracted": 1,
      "validArticles": 1,
      "genericTitles": 0,
      "extractErrors": 0,
      "avgBodyLen": 1571,
      "healthy": true,
      "error": null,
      "issueCategory": "",
      "status": "healthy",
      "consecutiveFailures": 0,
      "lastHealthyAt": "2026-07-20T06:49:57.248Z"
    },
    {
      "id": "ushuaia-oficial",
      "name": "Municipalidad de Ushuaia",
      "type": "html-index",
      "itemsFetched": 1,
      "linksResolved": 1,
      "articlesExtracted": 1,
      "validArticles": 1,
      "genericTitles": 0,
      "extractErrors": 0,
      "avgBodyLen": 1899,
      "healthy": true,
      "error": null,
      "issueCategory": "",
      "status": "healthy",
      "consecutiveFailures": 0,
      "lastHealthyAt": "2026-07-20T06:49:59.539Z"
    },
    {
      "id": "gobierno-tdf-oficial",
      "name": "Gobierno de Tierra del Fuego",
      "type": "rss",
      "itemsFetched": 1,
      "linksResolved": 1,
      "articlesExtracted": 1,
      "validArticles": 1,
      "genericTitles": 0,
      "extractErrors": 0,
      "avgBodyLen": 2566,
      "healthy": true,
      "error": null,
      "issueCategory": "",
      "status": "healthy",
      "consecutiveFailures": 0,
      "lastHealthyAt": "2026-07-20T06:50:02.841Z"
    },
    {
      "id": "tolhuin-oficial",
      "name": "Municipio de Tolhuin",
      "type": "rss",
      "itemsFetched": 1,
      "linksResolved": 1,
      "articlesExtracted": 1,
      "validArticles": 1,
      "genericTitles": 0,
      "extractErrors": 0,
      "avgBodyLen": 4476,
      "healthy": true,
      "error": null,
      "issueCategory": "",
      "status": "healthy",
      "consecutiveFailures": 0,
      "lastHealthyAt": "2026-07-20T06:50:03.603Z"
    },
    {
      "id": "actualidad-tdf",
      "name": "Actualidad TDF",
      "type": "rss",
      "itemsFetched": 5,
      "linksResolved": 5,
      "articlesExtracted": 5,
      "validArticles": 5,
      "genericTitles": 0,
      "extractErrors": 0,
      "avgBodyLen": 2867,
      "healthy": true,
      "error": null,
      "issueCategory": "",
      "status": "healthy",
      "consecutiveFailures": 0,
      "lastHealthyAt": "2026-07-20T06:50:07.090Z"
    },
    {
      "id": "el-rompehielos",
      "name": "El Rompehielos",
      "type": "rss",
      "itemsFetched": 4,
      "linksResolved": 4,
      "articlesExtracted": 4,
      "validArticles": 4,
      "genericTitles": 0,
      "extractErrors": 0,
      "avgBodyLen": 3809,
      "healthy": true,
      "error": null,
      "issueCategory": "",
      "status": "healthy",
      "consecutiveFailures": 0,
      "lastHealthyAt": "2026-07-20T06:50:10.255Z"
    },
    {
      "id": "radiofueguina",
      "name": "Radio Fueguina",
      "type": "html-index",
      "itemsFetched": 4,
      "linksResolved": 4,
      "articlesExtracted": 4,
      "validArticles": 4,
      "genericTitles": 0,
      "extractErrors": 0,
      "avgBodyLen": 1066,
      "healthy": true,
      "error": null,
      "issueCategory": "",
      "status": "healthy",
      "consecutiveFailures": 0,
      "lastHealthyAt": "2026-07-20T06:50:23.609Z"
    },
    {
      "id": "radio-universidad",
      "name": "Radio Universidad",
      "type": "rss",
      "itemsFetched": 4,
      "linksResolved": 4,
      "articlesExtracted": 4,
      "validArticles": 4,
      "genericTitles": 0,
      "extractErrors": 0,
      "avgBodyLen": 10551,
      "healthy": true,
      "error": null,
      "issueCategory": "",
      "status": "healthy",
      "consecutiveFailures": 0,
      "lastHealthyAt": "2026-07-20T06:50:33.897Z"
    },
    {
      "id": "sur54",
      "name": "Sur54",
      "type": "html-index",
      "itemsFetched": 5,
      "linksResolved": 5,
      "articlesExtracted": 5,
      "validArticles": 5,
      "genericTitles": 0,
      "extractErrors": 0,
      "avgBodyLen": 10043,
      "healthy": true,
      "error": null,
      "issueCategory": "",
      "status": "healthy",
      "consecutiveFailures": 0,
      "lastHealthyAt": "2026-07-20T06:50:36.889Z"
    },
    {
      "id": "ushuaia24",
      "name": "Ushuaia 24",
      "type": "html-index",
      "itemsFetched": 4,
      "linksResolved": 4,
      "articlesExtracted": 4,
      "validArticles": 4,
      "genericTitles": 0,
      "extractErrors": 0,
      "avgBodyLen": 7685,
      "healthy": true,
      "error": null,
      "issueCategory": "",
      "status": "healthy",
      "consecutiveFailures": 0,
      "lastHealthyAt": "2026-07-20T06:50:39.797Z"
    },
    {
      "id": "provincia23",
      "name": "Provincia 23",
      "type": "rss",
      "itemsFetched": 4,
      "linksResolved": 4,
      "articlesExtracted": 4,
      "validArticles": 4,
      "genericTitles": 0,
      "extractErrors": 0,
      "avgBodyLen": 6563,
      "healthy": true,
      "error": null,
      "issueCategory": "",
      "status": "healthy",
      "consecutiveFailures": 0,
      "lastHealthyAt": "2026-07-20T06:50:49.485Z"
    },
    {
      "id": "critica-sur",
      "name": "Critica Sur",
      "type": "html-index",
      "itemsFetched": 4,
      "linksResolved": 4,
      "articlesExtracted": 4,
      "validArticles": 4,
      "genericTitles": 0,
      "extractErrors": 0,
      "avgBodyLen": 3553,
      "healthy": true,
      "error": null,
      "issueCategory": "",
      "status": "healthy",
      "consecutiveFailures": 0,
      "lastHealthyAt": "2026-07-20T06:50:52.656Z"
    },
    {
      "id": "bing-tdf",
      "name": "Bing News — Tierra del Fuego",
      "type": "rss",
      "itemsFetched": 5,
      "linksResolved": 5,
      "articlesExtracted": 5,
      "validArticles": 3,
      "genericTitles": 0,
      "extractErrors": 0,
      "avgBodyLen": 7474,
      "healthy": true,
      "error": null,
      "issueCategory": "",
      "status": "healthy",
      "consecutiveFailures": 0,
      "lastHealthyAt": "2026-07-20T06:50:57.010Z"
    },
    {
      "id": "bing-rio-grande",
      "name": "Bing News — Río Grande",
      "type": "rss",
      "itemsFetched": 0,
      "linksResolved": 0,
      "articlesExtracted": 0,
      "validArticles": 0,
      "genericTitles": 0,
      "extractErrors": 0,
      "avgBodyLen": 0,
      "healthy": false,
      "error": "Unquoted attribute value\nLine: 0\nColumn: 42\nChar: h",
      "issueCategory": "fetch-error",
      "status": "unhealthy",
      "consecutiveFailures": 1,
      "lastHealthyAt": "2026-07-20T03:26:32.662Z"
    },
    {
      "id": "bing-ushuaia",
      "name": "Bing News — Ushuaia",
      "type": "rss",
      "itemsFetched": 4,
      "linksResolved": 4,
      "articlesExtracted": 4,
      "validArticles": 2,
      "genericTitles": 0,
      "extractErrors": 0,
      "avgBodyLen": 6307,
      "healthy": true,
      "error": null,
      "issueCategory": "",
      "status": "healthy",
      "consecutiveFailures": 0,
      "lastHealthyAt": "2026-07-20T06:51:00.285Z"
    },
    {
      "id": "bing-tolhuin",
      "name": "Bing News — Tolhuin",
      "type": "rss",
      "itemsFetched": 0,
      "linksResolved": 0,
      "articlesExtracted": 0,
      "validArticles": 0,
      "genericTitles": 0,
      "extractErrors": 0,
      "avgBodyLen": 0,
      "healthy": false,
      "error": "Unquoted attribute value\nLine: 0\nColumn: 42\nChar: h",
      "issueCategory": "fetch-error",
      "status": "unhealthy",
      "consecutiveFailures": 1,
      "lastHealthyAt": "2026-07-20T03:26:40.653Z"
    },
    {
      "id": "bing-malvinas",
      "name": "Bing News — Islas Malvinas",
      "type": "rss",
      "itemsFetched": 0,
      "linksResolved": 0,
      "articlesExtracted": 0,
      "validArticles": 0,
      "genericTitles": 0,
      "extractErrors": 0,
      "avgBodyLen": 0,
      "healthy": false,
      "error": "Feed not recognized as RSS 1 or 2.",
      "issueCategory": "fetch-error",
      "status": "unhealthy",
      "consecutiveFailures": 1,
      "lastHealthyAt": "2026-07-20T03:26:44.104Z"
    },
    {
      "id": "bing-antartida",
      "name": "Bing News — Antártida Argentina",
      "type": "rss",
      "itemsFetched": 3,
      "linksResolved": 3,
      "articlesExtracted": 3,
      "validArticles": 0,
      "genericTitles": 0,
      "extractErrors": 0,
      "avgBodyLen": 0,
      "healthy": false,
      "error": null,
      "issueCategory": "zero-valid-articles",
      "status": "unhealthy",
      "consecutiveFailures": 1,
      "lastHealthyAt": "2026-07-20T03:26:48.033Z"
    },
    {
      "id": "infobae-tdf",
      "name": "Infobae — Cobertura TdF",
      "type": "rss",
      "itemsFetched": 1,
      "linksResolved": 1,
      "articlesExtracted": 1,
      "validArticles": 1,
      "genericTitles": 0,
      "extractErrors": 0,
      "avgBodyLen": 13213,
      "healthy": true,
      "error": null,
      "issueCategory": "",
      "status": "healthy",
      "consecutiveFailures": 0,
      "lastHealthyAt": "2026-07-20T06:51:03.237Z"
    },
    {
      "id": "perfil-tdf",
      "name": "Perfil — Cobertura TdF",
      "type": "rss",
      "itemsFetched": 1,
      "linksResolved": 1,
      "articlesExtracted": 1,
      "validArticles": 1,
      "genericTitles": 0,
      "extractErrors": 0,
      "avgBodyLen": 10514,
      "healthy": true,
      "error": null,
      "issueCategory": "",
      "status": "healthy",
      "consecutiveFailures": 0,
      "lastHealthyAt": "2026-07-20T06:51:03.858Z"
    },
    {
      "id": "clarin-tdf",
      "name": "Clarín — Cobertura TdF",
      "type": "rss",
      "itemsFetched": 1,
      "linksResolved": 1,
      "articlesExtracted": 1,
      "validArticles": 1,
      "genericTitles": 0,
      "extractErrors": 0,
      "avgBodyLen": 4926,
      "healthy": true,
      "error": null,
      "issueCategory": "",
      "status": "healthy",
      "consecutiveFailures": 0,
      "lastHealthyAt": "2026-07-20T06:51:04.407Z"
    },
    {
      "id": "nacionales-infobae",
      "name": "Infobae — Nacionales",
      "type": "rss",
      "itemsFetched": 3,
      "linksResolved": 3,
      "articlesExtracted": 3,
      "validArticles": 3,
      "genericTitles": 0,
      "extractErrors": 0,
      "avgBodyLen": 5138,
      "healthy": true,
      "error": null,
      "issueCategory": "",
      "status": "healthy",
      "consecutiveFailures": 0,
      "lastHealthyAt": "2026-07-20T06:51:05.956Z"
    },
    {
      "id": "nacionales-perfil",
      "name": "Perfil — Nacionales",
      "type": "rss",
      "itemsFetched": 2,
      "linksResolved": 2,
      "articlesExtracted": 2,
      "validArticles": 2,
      "genericTitles": 0,
      "extractErrors": 0,
      "avgBodyLen": 7619,
      "healthy": true,
      "error": null,
      "issueCategory": "",
      "status": "healthy",
      "consecutiveFailures": 0,
      "lastHealthyAt": "2026-07-20T06:51:06.857Z"
    },
    {
      "id": "nacionales-la-nacion",
      "name": "La Nacion - Nacionales",
      "type": "rss",
      "itemsFetched": 3,
      "linksResolved": 3,
      "articlesExtracted": 3,
      "validArticles": 3,
      "genericTitles": 0,
      "extractErrors": 0,
      "avgBodyLen": 12099,
      "healthy": true,
      "error": null,
      "issueCategory": "",
      "status": "healthy",
      "consecutiveFailures": 0,
      "lastHealthyAt": "2026-07-20T06:51:08.818Z"
    },
    {
      "id": "nacionales-ambito",
      "name": "Ambito - Nacionales",
      "type": "rss",
      "itemsFetched": 3,
      "linksResolved": 3,
      "articlesExtracted": 3,
      "validArticles": 3,
      "genericTitles": 0,
      "extractErrors": 0,
      "avgBodyLen": 12668,
      "healthy": true,
      "error": null,
      "issueCategory": "",
      "status": "healthy",
      "consecutiveFailures": 0,
      "lastHealthyAt": "2026-07-20T06:51:10.487Z"
    },
    {
      "id": "nacionales-cronista",
      "name": "El Cronista - Nacionales",
      "type": "rss",
      "itemsFetched": 3,
      "linksResolved": 3,
      "articlesExtracted": 3,
      "validArticles": 3,
      "genericTitles": 0,
      "extractErrors": 0,
      "avgBodyLen": 5788,
      "healthy": true,
      "error": null,
      "issueCategory": "",
      "status": "healthy",
      "consecutiveFailures": 0,
      "lastHealthyAt": "2026-07-20T06:51:12.572Z"
    },
    {
      "id": "nacionales-tn",
      "name": "TN - Nacionales",
      "type": "rss",
      "itemsFetched": 3,
      "linksResolved": 3,
      "articlesExtracted": 3,
      "validArticles": 3,
      "genericTitles": 0,
      "extractErrors": 0,
      "avgBodyLen": 7104,
      "healthy": true,
      "error": null,
      "issueCategory": "",
      "status": "healthy",
      "consecutiveFailures": 0,
      "lastHealthyAt": "2026-07-20T06:51:14.367Z"
    },
    {
      "id": "mundo-google",
      "name": "Google News — Mundo",
      "type": "rss",
      "itemsFetched": 0,
      "linksResolved": 0,
      "articlesExtracted": 0,
      "validArticles": 0,
      "genericTitles": 0,
      "extractErrors": 0,
      "avgBodyLen": 0,
      "healthy": false,
      "error": "HTTP 503 en https://news.google.com/rss/headlines/section/topic/WORLD?hl=es-419&gl=AR&ceid=AR:es-419",
      "issueCategory": "fetch-error",
      "status": "unhealthy",
      "consecutiveFailures": 101,
      "lastHealthyAt": null
    },
    {
      "id": "mundo-clarin",
      "name": "Clarín — Mundo",
      "type": "rss",
      "itemsFetched": 3,
      "linksResolved": 3,
      "articlesExtracted": 3,
      "validArticles": 3,
      "genericTitles": 0,
      "extractErrors": 0,
      "avgBodyLen": 5513,
      "healthy": true,
      "error": null,
      "issueCategory": "",
      "status": "healthy",
      "consecutiveFailures": 0,
      "lastHealthyAt": "2026-07-20T06:51:21.588Z"
    },
    {
      "id": "mundo-bbc",
      "name": "BBC Mundo",
      "type": "rss",
      "itemsFetched": 3,
      "linksResolved": 3,
      "articlesExtracted": 3,
      "validArticles": 3,
      "genericTitles": 0,
      "extractErrors": 0,
      "avgBodyLen": 6700,
      "healthy": true,
      "error": null,
      "issueCategory": "",
      "status": "healthy",
      "consecutiveFailures": 0,
      "lastHealthyAt": "2026-07-20T06:51:23.430Z"
    },
    {
      "id": "mundo-dw",
      "name": "DW Espanol",
      "type": "rss",
      "itemsFetched": 3,
      "linksResolved": 3,
      "articlesExtracted": 3,
      "validArticles": 3,
      "genericTitles": 0,
      "extractErrors": 0,
      "avgBodyLen": 5232,
      "healthy": true,
      "error": null,
      "issueCategory": "",
      "status": "healthy",
      "consecutiveFailures": 0,
      "lastHealthyAt": "2026-07-20T06:51:26.088Z"
    },
    {
      "id": "mundo-france24",
      "name": "France 24 Espanol",
      "type": "rss",
      "itemsFetched": 3,
      "linksResolved": 3,
      "articlesExtracted": 3,
      "validArticles": 3,
      "genericTitles": 0,
      "extractErrors": 0,
      "avgBodyLen": 5958,
      "healthy": true,
      "error": null,
      "issueCategory": "",
      "status": "healthy",
      "consecutiveFailures": 0,
      "lastHealthyAt": "2026-07-20T06:51:27.647Z"
    },
    {
      "id": "mundo-elpais",
      "name": "El Pais - Internacional",
      "type": "rss",
      "itemsFetched": 3,
      "linksResolved": 3,
      "articlesExtracted": 0,
      "validArticles": 0,
      "genericTitles": 0,
      "extractErrors": 3,
      "avgBodyLen": 0,
      "healthy": false,
      "error": null,
      "issueCategory": "extractor-incompatible",
      "status": "unhealthy",
      "consecutiveFailures": 1,
      "lastHealthyAt": "2026-07-20T03:27:19.246Z"
    },
    {
      "id": "mundo-bing",
      "name": "Bing News — Mundo",
      "type": "rss",
      "itemsFetched": 3,
      "linksResolved": 3,
      "articlesExtracted": 3,
      "validArticles": 1,
      "genericTitles": 0,
      "extractErrors": 0,
      "avgBodyLen": 2024,
      "healthy": true,
      "error": null,
      "issueCategory": "",
      "status": "healthy",
      "consecutiveFailures": 0,
      "lastHealthyAt": "2026-07-20T06:51:31.127Z"
    }
  ],
  "unhealthyIds": [
    "bing-rio-grande",
    "bing-tolhuin",
    "bing-malvinas",
    "bing-antartida",
    "mundo-google",
    "mundo-elpais"
  ]
}