{
  "generatedAt": "2026-07-21T00:19:42.122Z",
  "summary": {
    "configured": 34,
    "healthy": 30,
    "unhealthy": 4,
    "productive": 30,
    "zeroResults": 3,
    "failed": 0
  },
  "sources": [
    {
      "id": "rio-grande-oficial",
      "name": "Municipio de Río Grande",
      "type": "rss",
      "itemsFetched": 1,
      "linksResolved": 1,
      "articlesExtracted": 1,
      "validArticles": 1,
      "genericTitles": 0,
      "extractErrors": 0,
      "avgBodyLen": 1831,
      "healthy": true,
      "error": null,
      "issueCategory": "",
      "status": "healthy",
      "consecutiveFailures": 0,
      "lastHealthyAt": "2026-07-21T00:18:10.175Z"
    },
    {
      "id": "ushuaia-oficial",
      "name": "Municipalidad de Ushuaia",
      "type": "html-index",
      "itemsFetched": 1,
      "linksResolved": 1,
      "articlesExtracted": 1,
      "validArticles": 1,
      "genericTitles": 0,
      "extractErrors": 0,
      "avgBodyLen": 1899,
      "healthy": true,
      "error": null,
      "issueCategory": "",
      "status": "healthy",
      "consecutiveFailures": 0,
      "lastHealthyAt": "2026-07-21T00:18:12.671Z"
    },
    {
      "id": "gobierno-tdf-oficial",
      "name": "Gobierno de Tierra del Fuego",
      "type": "rss",
      "itemsFetched": 1,
      "linksResolved": 1,
      "articlesExtracted": 1,
      "validArticles": 1,
      "genericTitles": 0,
      "extractErrors": 0,
      "avgBodyLen": 2378,
      "healthy": true,
      "error": null,
      "issueCategory": "",
      "status": "healthy",
      "consecutiveFailures": 0,
      "lastHealthyAt": "2026-07-21T00:18:15.630Z"
    },
    {
      "id": "tolhuin-oficial",
      "name": "Municipio de Tolhuin",
      "type": "rss",
      "itemsFetched": 1,
      "linksResolved": 1,
      "articlesExtracted": 1,
      "validArticles": 1,
      "genericTitles": 0,
      "extractErrors": 0,
      "avgBodyLen": 4525,
      "healthy": true,
      "error": null,
      "issueCategory": "",
      "status": "healthy",
      "consecutiveFailures": 0,
      "lastHealthyAt": "2026-07-21T00:18:16.439Z"
    },
    {
      "id": "actualidad-tdf",
      "name": "Actualidad TDF",
      "type": "rss",
      "itemsFetched": 5,
      "linksResolved": 5,
      "articlesExtracted": 5,
      "validArticles": 5,
      "genericTitles": 0,
      "extractErrors": 0,
      "avgBodyLen": 3127,
      "healthy": true,
      "error": null,
      "issueCategory": "",
      "status": "healthy",
      "consecutiveFailures": 0,
      "lastHealthyAt": "2026-07-21T00:18:20.027Z"
    },
    {
      "id": "el-rompehielos",
      "name": "El Rompehielos",
      "type": "rss",
      "itemsFetched": 4,
      "linksResolved": 4,
      "articlesExtracted": 4,
      "validArticles": 4,
      "genericTitles": 0,
      "extractErrors": 0,
      "avgBodyLen": 3476,
      "healthy": true,
      "error": null,
      "issueCategory": "",
      "status": "healthy",
      "consecutiveFailures": 0,
      "lastHealthyAt": "2026-07-21T00:18:23.867Z"
    },
    {
      "id": "radiofueguina",
      "name": "Radio Fueguina",
      "type": "html-index",
      "itemsFetched": 4,
      "linksResolved": 4,
      "articlesExtracted": 4,
      "validArticles": 4,
      "genericTitles": 0,
      "extractErrors": 0,
      "avgBodyLen": 1066,
      "healthy": true,
      "error": null,
      "issueCategory": "",
      "status": "healthy",
      "consecutiveFailures": 0,
      "lastHealthyAt": "2026-07-21T00:18:30.635Z"
    },
    {
      "id": "radio-universidad",
      "name": "Radio Universidad",
      "type": "rss",
      "itemsFetched": 4,
      "linksResolved": 4,
      "articlesExtracted": 4,
      "validArticles": 4,
      "genericTitles": 0,
      "extractErrors": 0,
      "avgBodyLen": 7376,
      "healthy": true,
      "error": null,
      "issueCategory": "",
      "status": "healthy",
      "consecutiveFailures": 0,
      "lastHealthyAt": "2026-07-21T00:18:37.129Z"
    },
    {
      "id": "sur54",
      "name": "Sur54",
      "type": "html-index",
      "itemsFetched": 5,
      "linksResolved": 5,
      "articlesExtracted": 5,
      "validArticles": 5,
      "genericTitles": 0,
      "extractErrors": 0,
      "avgBodyLen": 9361,
      "healthy": true,
      "error": null,
      "issueCategory": "",
      "status": "healthy",
      "consecutiveFailures": 0,
      "lastHealthyAt": "2026-07-21T00:18:40.291Z"
    },
    {
      "id": "ushuaia24",
      "name": "Ushuaia 24",
      "type": "html-index",
      "itemsFetched": 4,
      "linksResolved": 4,
      "articlesExtracted": 4,
      "validArticles": 4,
      "genericTitles": 0,
      "extractErrors": 0,
      "avgBodyLen": 7629,
      "healthy": true,
      "error": null,
      "issueCategory": "",
      "status": "healthy",
      "consecutiveFailures": 0,
      "lastHealthyAt": "2026-07-21T00:18:42.965Z"
    },
    {
      "id": "provincia23",
      "name": "Provincia 23",
      "type": "rss",
      "itemsFetched": 4,
      "linksResolved": 4,
      "articlesExtracted": 4,
      "validArticles": 4,
      "genericTitles": 0,
      "extractErrors": 0,
      "avgBodyLen": 6563,
      "healthy": true,
      "error": null,
      "issueCategory": "",
      "status": "healthy",
      "consecutiveFailures": 0,
      "lastHealthyAt": "2026-07-21T00:18:49.756Z"
    },
    {
      "id": "critica-sur",
      "name": "Critica Sur",
      "type": "html-index",
      "itemsFetched": 4,
      "linksResolved": 4,
      "articlesExtracted": 4,
      "validArticles": 4,
      "genericTitles": 0,
      "extractErrors": 0,
      "avgBodyLen": 2438,
      "healthy": true,
      "error": null,
      "issueCategory": "",
      "status": "healthy",
      "consecutiveFailures": 0,
      "lastHealthyAt": "2026-07-21T00:18:53.553Z"
    },
    {
      "id": "bing-tdf",
      "name": "Bing News — Tierra del Fuego",
      "type": "rss",
      "itemsFetched": 5,
      "linksResolved": 5,
      "articlesExtracted": 5,
      "validArticles": 5,
      "genericTitles": 0,
      "extractErrors": 0,
      "avgBodyLen": 12174,
      "healthy": true,
      "error": null,
      "issueCategory": "",
      "status": "healthy",
      "consecutiveFailures": 0,
      "lastHealthyAt": "2026-07-21T00:18:57.315Z"
    },
    {
      "id": "bing-rio-grande",
      "name": "Bing News — Río Grande",
      "type": "rss",
      "itemsFetched": 4,
      "linksResolved": 4,
      "articlesExtracted": 4,
      "validArticles": 3,
      "genericTitles": 1,
      "extractErrors": 0,
      "avgBodyLen": 4829,
      "healthy": true,
      "error": null,
      "issueCategory": "",
      "status": "healthy",
      "consecutiveFailures": 0,
      "lastHealthyAt": "2026-07-21T00:19:01.594Z"
    },
    {
      "id": "bing-ushuaia",
      "name": "Bing News — Ushuaia",
      "type": "rss",
      "itemsFetched": 4,
      "linksResolved": 4,
      "articlesExtracted": 4,
      "validArticles": 4,
      "genericTitles": 0,
      "extractErrors": 0,
      "avgBodyLen": 6535,
      "healthy": true,
      "error": null,
      "issueCategory": "",
      "status": "healthy",
      "consecutiveFailures": 0,
      "lastHealthyAt": "2026-07-21T00:19:06.773Z"
    },
    {
      "id": "bing-tolhuin",
      "name": "Bing News — Tolhuin",
      "type": "rss",
      "itemsFetched": 3,
      "linksResolved": 3,
      "articlesExtracted": 3,
      "validArticles": 3,
      "genericTitles": 0,
      "extractErrors": 0,
      "avgBodyLen": 6485,
      "healthy": true,
      "error": null,
      "issueCategory": "",
      "status": "healthy",
      "consecutiveFailures": 0,
      "lastHealthyAt": "2026-07-21T00:19:08.910Z"
    },
    {
      "id": "bing-malvinas",
      "name": "Bing News — Islas Malvinas",
      "type": "rss",
      "itemsFetched": 3,
      "linksResolved": 3,
      "articlesExtracted": 3,
      "validArticles": 3,
      "genericTitles": 0,
      "extractErrors": 0,
      "avgBodyLen": 6350,
      "healthy": true,
      "error": null,
      "issueCategory": "",
      "status": "healthy",
      "consecutiveFailures": 0,
      "lastHealthyAt": "2026-07-21T00:19:12.777Z"
    },
    {
      "id": "bing-antartida",
      "name": "Bing News — Antártida Argentina",
      "type": "rss",
      "itemsFetched": 3,
      "linksResolved": 3,
      "articlesExtracted": 3,
      "validArticles": 3,
      "genericTitles": 0,
      "extractErrors": 0,
      "avgBodyLen": 7282,
      "healthy": true,
      "error": null,
      "issueCategory": "",
      "status": "healthy",
      "consecutiveFailures": 0,
      "lastHealthyAt": "2026-07-21T00:19:15.526Z"
    },
    {
      "id": "infobae-tdf",
      "name": "Infobae — Cobertura TdF",
      "type": "rss",
      "itemsFetched": 0,
      "linksResolved": 0,
      "articlesExtracted": 0,
      "validArticles": 0,
      "genericTitles": 0,
      "extractErrors": 0,
      "avgBodyLen": 0,
      "healthy": false,
      "error": null,
      "issueCategory": "zero-items",
      "status": "unhealthy",
      "consecutiveFailures": 8,
      "lastHealthyAt": "2026-07-20T06:51:03.237Z"
    },
    {
      "id": "perfil-tdf",
      "name": "Perfil — Cobertura TdF",
      "type": "rss",
      "itemsFetched": 0,
      "linksResolved": 0,
      "articlesExtracted": 0,
      "validArticles": 0,
      "genericTitles": 0,
      "extractErrors": 0,
      "avgBodyLen": 0,
      "healthy": false,
      "error": null,
      "issueCategory": "zero-items",
      "status": "unhealthy",
      "consecutiveFailures": 5,
      "lastHealthyAt": "2026-07-20T18:08:08.282Z"
    },
    {
      "id": "clarin-tdf",
      "name": "Clarín — Cobertura TdF",
      "type": "rss",
      "itemsFetched": 0,
      "linksResolved": 0,
      "articlesExtracted": 0,
      "validArticles": 0,
      "genericTitles": 0,
      "extractErrors": 0,
      "avgBodyLen": 0,
      "healthy": false,
      "error": null,
      "issueCategory": "zero-items",
      "status": "unhealthy",
      "consecutiveFailures": 2,
      "lastHealthyAt": "2026-07-20T23:04:32.812Z"
    },
    {
      "id": "nacionales-infobae",
      "name": "Infobae — Nacionales",
      "type": "rss",
      "itemsFetched": 3,
      "linksResolved": 3,
      "articlesExtracted": 3,
      "validArticles": 3,
      "genericTitles": 0,
      "extractErrors": 0,
      "avgBodyLen": 14717,
      "healthy": true,
      "error": null,
      "issueCategory": "",
      "status": "healthy",
      "consecutiveFailures": 0,
      "lastHealthyAt": "2026-07-21T00:19:17.377Z"
    },
    {
      "id": "nacionales-perfil",
      "name": "Perfil — Nacionales",
      "type": "rss",
      "itemsFetched": 2,
      "linksResolved": 2,
      "articlesExtracted": 2,
      "validArticles": 2,
      "genericTitles": 0,
      "extractErrors": 0,
      "avgBodyLen": 4847,
      "healthy": true,
      "error": null,
      "issueCategory": "",
      "status": "healthy",
      "consecutiveFailures": 0,
      "lastHealthyAt": "2026-07-21T00:19:18.379Z"
    },
    {
      "id": "nacionales-la-nacion",
      "name": "La Nacion - Nacionales",
      "type": "rss",
      "itemsFetched": 3,
      "linksResolved": 3,
      "articlesExtracted": 3,
      "validArticles": 3,
      "genericTitles": 0,
      "extractErrors": 0,
      "avgBodyLen": 10943,
      "healthy": true,
      "error": null,
      "issueCategory": "",
      "status": "healthy",
      "consecutiveFailures": 0,
      "lastHealthyAt": "2026-07-21T00:19:20.377Z"
    },
    {
      "id": "nacionales-ambito",
      "name": "Ambito - Nacionales",
      "type": "rss",
      "itemsFetched": 3,
      "linksResolved": 3,
      "articlesExtracted": 3,
      "validArticles": 3,
      "genericTitles": 0,
      "extractErrors": 0,
      "avgBodyLen": 15898,
      "healthy": true,
      "error": null,
      "issueCategory": "",
      "status": "healthy",
      "consecutiveFailures": 0,
      "lastHealthyAt": "2026-07-21T00:19:21.824Z"
    },
    {
      "id": "nacionales-cronista",
      "name": "El Cronista - Nacionales",
      "type": "rss",
      "itemsFetched": 3,
      "linksResolved": 3,
      "articlesExtracted": 3,
      "validArticles": 3,
      "genericTitles": 0,
      "extractErrors": 0,
      "avgBodyLen": 7553,
      "healthy": true,
      "error": null,
      "issueCategory": "",
      "status": "healthy",
      "consecutiveFailures": 0,
      "lastHealthyAt": "2026-07-21T00:19:23.838Z"
    },
    {
      "id": "nacionales-tn",
      "name": "TN - Nacionales",
      "type": "rss",
      "itemsFetched": 3,
      "linksResolved": 3,
      "articlesExtracted": 3,
      "validArticles": 3,
      "genericTitles": 0,
      "extractErrors": 0,
      "avgBodyLen": 6958,
      "healthy": true,
      "error": null,
      "issueCategory": "",
      "status": "healthy",
      "consecutiveFailures": 0,
      "lastHealthyAt": "2026-07-21T00:19:26.388Z"
    },
    {
      "id": "mundo-google",
      "name": "Google News — Mundo",
      "type": "rss",
      "itemsFetched": 3,
      "linksResolved": 3,
      "articlesExtracted": 3,
      "validArticles": 0,
      "genericTitles": 0,
      "extractErrors": 0,
      "avgBodyLen": 0,
      "healthy": false,
      "error": null,
      "issueCategory": "zero-valid-articles",
      "status": "unhealthy",
      "consecutiveFailures": 109,
      "lastHealthyAt": null
    },
    {
      "id": "mundo-clarin",
      "name": "Clarín — Mundo",
      "type": "rss",
      "itemsFetched": 3,
      "linksResolved": 3,
      "articlesExtracted": 3,
      "validArticles": 3,
      "genericTitles": 0,
      "extractErrors": 0,
      "avgBodyLen": 4434,
      "healthy": true,
      "error": null,
      "issueCategory": "",
      "status": "healthy",
      "consecutiveFailures": 0,
      "lastHealthyAt": "2026-07-21T00:19:30.140Z"
    },
    {
      "id": "mundo-bbc",
      "name": "BBC Mundo",
      "type": "rss",
      "itemsFetched": 3,
      "linksResolved": 3,
      "articlesExtracted": 3,
      "validArticles": 3,
      "genericTitles": 0,
      "extractErrors": 0,
      "avgBodyLen": 14397,
      "healthy": true,
      "error": null,
      "issueCategory": "",
      "status": "healthy",
      "consecutiveFailures": 0,
      "lastHealthyAt": "2026-07-21T00:19:31.748Z"
    },
    {
      "id": "mundo-dw",
      "name": "DW Espanol",
      "type": "rss",
      "itemsFetched": 3,
      "linksResolved": 3,
      "articlesExtracted": 3,
      "validArticles": 3,
      "genericTitles": 0,
      "extractErrors": 0,
      "avgBodyLen": 4150,
      "healthy": true,
      "error": null,
      "issueCategory": "",
      "status": "healthy",
      "consecutiveFailures": 0,
      "lastHealthyAt": "2026-07-21T00:19:34.914Z"
    },
    {
      "id": "mundo-france24",
      "name": "France 24 Espanol",
      "type": "rss",
      "itemsFetched": 3,
      "linksResolved": 3,
      "articlesExtracted": 3,
      "validArticles": 3,
      "genericTitles": 0,
      "extractErrors": 0,
      "avgBodyLen": 6058,
      "healthy": true,
      "error": null,
      "issueCategory": "",
      "status": "healthy",
      "consecutiveFailures": 0,
      "lastHealthyAt": "2026-07-21T00:19:36.792Z"
    },
    {
      "id": "mundo-elpais",
      "name": "El Pais - Internacional",
      "type": "rss",
      "itemsFetched": 3,
      "linksResolved": 3,
      "articlesExtracted": 1,
      "validArticles": 1,
      "genericTitles": 0,
      "extractErrors": 2,
      "avgBodyLen": 13154,
      "healthy": true,
      "error": null,
      "issueCategory": "",
      "status": "healthy",
      "consecutiveFailures": 0,
      "lastHealthyAt": "2026-07-21T00:19:39.824Z"
    },
    {
      "id": "mundo-bing",
      "name": "Bing News — Mundo",
      "type": "rss",
      "itemsFetched": 3,
      "linksResolved": 3,
      "articlesExtracted": 3,
      "validArticles": 3,
      "genericTitles": 0,
      "extractErrors": 0,
      "avgBodyLen": 13691,
      "healthy": true,
      "error": null,
      "issueCategory": "",
      "status": "healthy",
      "consecutiveFailures": 0,
      "lastHealthyAt": "2026-07-21T00:19:42.120Z"
    }
  ],
  "unhealthyIds": [
    "infobae-tdf",
    "perfil-tdf",
    "clarin-tdf",
    "mundo-google"
  ]
}